qcvharmonizer/__init__.py
qcvharmonizer/qcvharmonizer.py
qcvharmonizer-0.1.9.dist-info/METADATA
qcvharmonizer-0.1.9.dist-info/WHEEL
qcvharmonizer-0.1.9.dist-info/entry_points.txt
qcvharmonizer-0.1.9.dist-info/top_level.txt
qcvharmonizer-0.1.9.dist-info/RECORD
